README
setup.py
digitalnz/__init__.py
digitalnz/request.py
digitalnz/response.py
digitalnz.egg-info/PKG-INFO
digitalnz.egg-info/SOURCES.txt
digitalnz.egg-info/dependency_links.txt
digitalnz.egg-info/top_level.txt