Metadata-Version: 1.0
Name: digitalnz
Version: 0.2
Summary: Interact with the Digital New Zealand API
Home-page: http://bitbucket.org/anarchivist/digitalnz/
Author: Mark A. Matienzo
Author-email: mark@matienzo.org
License: GPL
Platform: UNKNOWN
Classifier: Intended Audience :: Education
Classifier: Intended Audience :: Developers
Classifier: Intended Audience :: Information Technology
Classifier: License :: OSI Approved :: GNU General Public License (GPL)
Classifier: Programming Language :: Python
Classifier: Development Status :: 3 - Alpha
